MANIFEST.in
setup.py
django_quickbooks_online.egg-info/PKG-INFO
django_quickbooks_online.egg-info/SOURCES.txt
django_quickbooks_online.egg-info/dependency_links.txt
django_quickbooks_online.egg-info/requires.txt
django_quickbooks_online.egg-info/top_level.txt
quickbooks/__init__.py
quickbooks/api.py
quickbooks/context_processors.py
quickbooks/exceptions.py
quickbooks/models.py
quickbooks/signals.py
quickbooks/tests.py
quickbooks/urls.py
quickbooks/views.py
quickbooks/migrations/0001_initial.py
quickbooks/migrations/0002_auto__chg_field_quickbookstoken_access_token__chg_field_quickbookstoke.py
quickbooks/migrations/__init__.py
quickbooks/templates/oauth_callback.html
quickbooks/templatetags/__init__.py
quickbooks/templatetags/quickbooks_tags.py