Metadata-Version: 1.0
Name: django-quickbooks-online
Version: 0.2
Summary: Django Quickbooks App
Home-page: http://github.com/grue/django-quickbooks-online
Author: Joshua Sorenson
Author-email: josh@grue.io
License: MIT License
Keywords: django quickbooks intuit
Platform: UNKNOWN
